nitslog/__init__.py
nitslog/logger.py
nitslog-1.0.0.dist-info/METADATA
nitslog-1.0.0.dist-info/WHEEL
nitslog-1.0.0.dist-info/entry_points.txt
nitslog-1.0.0.dist-info/top_level.txt
nitslog-1.0.0.dist-info/RECORD
