Metadata-Version: 2.2
Name: nitslog
Version: 1.0.0
Summary: A simple task logger application
Home-page: https://github.com/yourusername/tasklogger
Author: Nityanand Mathur
Author-email: nityanandmathur@gmail.com
Classifier: Programming Language :: Python :: 3
Classifier: License :: OSI Approved :: MIT License
Classifier: Operating System :: OS Independent
Requires-Python: >=3.6
Requires-Dist: rich
Requires-Dist: prompt_toolkit
Dynamic: author
Dynamic: author-email
Dynamic: classifier
Dynamic: description
Dynamic: description-content-type
Dynamic: home-page
Dynamic: requires-dist
Dynamic: requires-python
Dynamic: summary
